setup.py
wdk.py
WDK.egg-info/PKG-INFO
WDK.egg-info/SOURCES.txt
WDK.egg-info/dependency_links.txt
WDK.egg-info/top_level.txt