Metadata-Version: 1.1
Name: WDK
Version: 1.0.1b1
Summary: Python API for D-Link WDK
Home-page: https://github.com/sundhaug92/dlink-wdk
Author: Martin Sundhaug
Author-email: martinsundhaug@gmail.com
License: MIT
Keywords: dlink dir100 wdk web cliget api
Platform: UNKNOWN
Classifier: Programming Language :: Python
Classifier: Programming Language :: Python :: 2
Classifier: Programming Language :: Python :: 2.7
Classifier: Programming Language :: Python :: 2 :: Only
Classifier: Development Status :: 4 - Beta
Classifier: Intended Audience :: Developers
Classifier: License :: OSI Approved :: MIT License
Classifier: Operating System :: OS Independent
Classifier: Topic :: Internet :: WWW/HTTP
Classifier: Topic :: Security
Classifier: Topic :: Software Development :: Embedded Systems
Classifier: Topic :: Software Development :: Libraries
